[{"situation": "expected_negative", "greater_p_value": 1.0, "lower_p_value": 9.992558804935896e-86, "main_fitness": -398.7435240614765, "background_fitness": -396.88453237591335, "hamming_distance": 3, "time": 2.9310507774353027}, {"situation": "expected_negative", "greater_p_value": 0.9999999915990472, "lower_p_value": 8.404733238684257e-09, "main_fitness": -396.7851385739481, "background_fitness": -396.2488051146385, "hamming_distance": 8, "time": 2.8682918548583984}, {"situation": "expected_positive", "greater_p_value": 1.0, "lower_p_value": 5.0708937260330786e-48, "main_fitness": -396.55945011337866, "background_fitness": -396.9405770030234, "hamming_distance": 6, "time": 2.851299524307251}, {"situation": "expected_negative", "greater_p_value": 5.763211629929434e-110, "lower_p_value": 1.0, "main_fitness": -394.39027311665416, "background_fitness": -393.6900841521794, "hamming_distance": 7, "time": 2.9235827922821045}, {"situation": "expected_positive", "greater_p_value": 3.974304865137358e-06, "lower_p_value": 0.9999960271328523, "main_fitness": -395.26087314184934, "background_fitness": -395.6618731418493, "hamming_distance": 2, "time": 2.913625717163086}, {"situation": "expected_negative", "greater_p_value": 0.9999999999948774, "lower_p_value": 5.125348255360798e-12, "main_fitness": -396.4723451751071, "background_fitness": -393.694152053414, "hamming_distance": 7, "time": 2.858175277709961}, {"situation": "expected_negative", "greater_p_value": 1.0, "lower_p_value": 9.113587462357994e-216, "main_fitness": -400.0811831695641, "background_fitness": -396.66821491559585, "hamming_distance": 6, "time": 2.952273368835449}, {"situation": "expected_positive", "greater_p_value": 5.6084957801165784e-33, "lower_p_value": 1.0, "main_fitness": -397.1378619299572, "background_fitness": -397.6828495842782, "hamming_distance": 2, "time": 2.863267660140991}, {"situation": "expected_positive", "greater_p_value": 3.854222268416601e-44, "lower_p_value": 1.0, "main_fitness": -395.056968915344, "background_fitness": -395.57524968505925, "hamming_distance": 3, "time": 2.8782219886779785}, {"situation": "expected_negative", "greater_p_value": 1.0, "lower_p_value": 6.624533258069032e-66, "main_fitness": -398.3442166792643, "background_fitness": -395.5147542202066, "hamming_distance": 7, "time": 2.86730694770813}, {"situation": "expected_negative", "greater_p_value": 1.0, "lower_p_value": 4.710659552744758e-202, "main_fitness": -399.88021982867224, "background_fitness": -399.64400529100527, "hamming_distance": 6, "time": 2.8572330474853516}, {"situation": "expected_positive", "greater_p_value": 2.1098654571010375e-103, "lower_p_value": 1.0, "main_fitness": -395.7727254976065, "background_fitness": -396.8381623834719, "hamming_distance": 5, "time": 2.918355703353882}, {"situation": "expected_negative", "greater_p_value": 0.0289895948482224, "lower_p_value": 0.9710155262152134, "main_fitness": -394.8296342907533, "background_fitness": -394.07190236835476, "hamming_distance": 4, "time": 2.8852856159210205}, {"situation": "expected_positive", "greater_p_value": 1.809371301288079e-14, "lower_p_value": 0.9999999999999819, "main_fitness": -396.5151137566138, "background_fitness": -396.9532496850592, "hamming_distance": 6, "time": 2.914198160171509}, {"situation": "expected_negative", "greater_p_value": 2.1653340782307077e-142, "lower_p_value": 1.0, "main_fitness": -395.29902557319224, "background_fitness": -393.74468720080625, "hamming_distance": 3, "time": 2.875783920288086}, {"situation": "expected_positive", "greater_p_value": 6.3634513127865994e-121, "lower_p_value": 1.0, "main_fitness": -392.04736948853616, "background_fitness": -392.0566287477954, "hamming_distance": 2, "time": 2.9262514114379883}, {"situation": "expected_positive", "greater_p_value": 9.186985699814282e-79, "lower_p_value": 1.0, "main_fitness": -395.8699480977577, "background_fitness": -399.19557180650037, "hamming_distance": 7, "time": 2.949320077896118}, {"situation": "expected_negative", "greater_p_value": 1.0, "lower_p_value": 1.221845153980526e-23, "main_fitness": -397.1844050138574, "background_fitness": -394.8918607961703, "hamming_distance": 7, "time": 2.881300210952759}, {"situation": "expected_positive", "greater_p_value": 3.2356604821359915e-266, "lower_p_value": 1.0, "main_fitness": -392.8971696900983, "background_fitness": -395.2542581254724, "hamming_distance": 3, "time": 2.9612536430358887}, {"situation": "expected_negative", "greater_p_value": 1.0, "lower_p_value": 7.206602570318182e-24, "main_fitness": -396.24953086419754, "background_fitness": -395.15969299571685, "hamming_distance": 7, "time": 2.8393361568450928}, {"situation": "expected_negative", "greater_p_value": 1.7558869564500048e-165, "lower_p_value": 1.0, "main_fitness": -395.2649706475183, "background_fitness": -395.12608175862937, "hamming_distance": 1, "time": 2.906216621398926}, {"situation": "expected_positive", "greater_p_value": 0.9999999999999922, "lower_p_value": 7.828748000757811e-15, "main_fitness": -397.4649129503653, "background_fitness": -397.6209219261779, "hamming_distance": 7, "time": 2.880237579345703}, {"situation": "expected_negative", "greater_p_value": 7.087310850276575e-172, "lower_p_value": 1.0, "main_fitness": -395.85028143109093, "background_fitness": -395.0348759133283, "hamming_distance": 8, "time": 2.8351776599884033}, {"situation": "expected_positive", "greater_p_value": 2.442582421746863e-60, "lower_p_value": 1.0, "main_fitness": -396.5427784076594, "background_fitness": -396.8364212648022, "hamming_distance": 2, "time": 3.007336139678955}, {"situation": "expected_positive", "greater_p_value": 2.1277124346137022e-95, "lower_p_value": 1.0, "main_fitness": -396.8717199546486, "background_fitness": -399.54765822625353, "hamming_distance": 8, "time": 2.8818509578704834}, {"situation": "expected_negative", "greater_p_value": 1.0, "lower_p_value": 3.7362935699852484e-78, "main_fitness": -399.54765822625353, "background_fitness": -397.9549433106576, "hamming_distance": 7, "time": 2.848792552947998}, {"situation": "expected_negative", "greater_p_value": 1.0, "lower_p_value": 6.576788625723074e-34, "main_fitness": -396.93442101284955, "background_fitness": -396.61564840010084, "hamming_distance": 7, "time": 2.9202582836151123}, {"situation": "expected_negative", "greater_p_value": 1.0, "lower_p_value": 2.6927365667432434e-116, "main_fitness": -399.0654105568153, "background_fitness": -397.88884278155706, "hamming_distance": 6, "time": 2.861232042312622}, {"situation": "expected_positive", "greater_p_value": 1.9353003353592214e-163, "lower_p_value": 1.0, "main_fitness": -394.59014953388765, "background_fitness": -396.8373408919124, "hamming_distance": 6, "time": 2.8382463455200195}, {"situation": "expected_negative", "greater_p_value": 1.0, "lower_p_value": 4.084376119518319e-28, "main_fitness": -399.49357205845297, "background_fitness": -396.78763857394813, "hamming_distance": 8, "time": 2.863304615020752}, {"situation": "expected_negative", "greater_p_value": 1.0, "lower_p_value": 4.06436144722096e-39, "main_fitness": -397.5409978584026, "background_fitness": -396.99385563114134, "hamming_distance": 6, "time": 2.907581329345703}, {"situation": "expected_positive", "greater_p_value": 7.078743361049802e-21, "lower_p_value": 1.0, "main_fitness": -395.2154391534392, "background_fitness": -396.14105265810036, "hamming_distance": 6, "time": 3.6691341400146484}, {"situation": "expected_negative", "greater_p_value": 1.0, "lower_p_value": 2.0493022806626998e-222, "main_fitness": -400.7547226001512, "background_fitness": -398.0242747543462, "hamming_distance": 6, "time": 3.0938501358032227}, {"situation": "expected_positive", "greater_p_value": 8.938163166800293e-131, "lower_p_value": 1.0, "main_fitness": -394.273346340388, "background_fitness": -399.19557180650037, "hamming_distance": 8, "time": 3.8006720542907715}, {"situation": "expected_negative", "greater_p_value": 0.9580651349786026, "lower_p_value": 0.041941799465419316, "main_fitness": -396.7355592088687, "background_fitness": -393.77279050138577, "hamming_distance": 6, "time": 3.111673355102539}, {"situation": "expected_negative", "greater_p_value": 1.5896503683697745e-10, "lower_p_value": 0.9999999998411142, "main_fitness": -396.8011908541195, "background_fitness": -395.1683445452255, "hamming_distance": 6, "time": 2.9740664958953857}, {"situation": "expected_positive", "greater_p_value": 1.0993201700371451e-83, "lower_p_value": 1.0, "main_fitness": -395.0761943814563, "background_fitness": -395.6877768959436, "hamming_distance": 6, "time": 2.929269313812256}, {"situation": "expected_negative", "greater_p_value": 1.0, "lower_p_value": 1.1516502175700483e-137, "main_fitness": -400.04375774754345, "background_fitness": -398.36671907281436, "hamming_distance": 7, "time": 3.192168712615967}, {"situation": "expected_positive", "greater_p_value": 1.3371295628837995e-10, "lower_p_value": 0.999999999866354, "main_fitness": -395.73902632905015, "background_fitness": -395.84902632905016, "hamming_distance": 1, "time": 3.023801326751709}, {"situation": "expected_positive", "greater_p_value": 1.0, "lower_p_value": 6.41264012011378e-167, "main_fitness": -400.2909138321995, "background_fitness": -400.42757936507934, "hamming_distance": 7, "time": 3.0556721687316895}, {"situation": "expected_negative", "greater_p_value": 1.0, "lower_p_value": 2.4542834292729015e-245, "main_fitness": -400.97600755857906, "background_fitness": -397.1326909800958, "hamming_distance": 8, "time": 3.396359920501709}, {"situation": "expected_positive", "greater_p_value": 3.739500897805682e-156, "lower_p_value": 1.0, "main_fitness": -394.59014953388765, "background_fitness": -396.8373408919124, "hamming_distance": 6, "time": 2.8692944049835205}, {"situation": "expected_positive", "greater_p_value": 8.460009598648527e-196, "lower_p_value": 1.0, "main_fitness": -394.78183106575966, "background_fitness": -396.1709274376418, "hamming_distance": 6, "time": 2.9631900787353516}, {"situation": "expected_negative", "greater_p_value": 1.0, "lower_p_value": 5.182781872103305e-279, "main_fitness": -400.37491181657845, "background_fitness": -397.3012928949358, "hamming_distance": 7, "time": 2.861088991165161}, {"situation": "expected_positive", "greater_p_value": 1.0, "lower_p_value": 4.4507263474520954e-178, "main_fitness": -400.98693512219705, "background_fitness": -401.01982237339377, "hamming_distance": 7, "time": 2.8882153034210205}, {"situation": "expected_positive", "greater_p_value": 9.181625403476956e-37, "lower_p_value": 1.0, "main_fitness": -395.9409035021416, "background_fitness": -397.8363303099017, "hamming_distance": 6, "time": 2.8791260719299316}, {"situation": "expected_negative", "greater_p_value": 0.8380685553530489, "lower_p_value": 0.1619504356594701, "main_fitness": -394.9839890400605, "background_fitness": -394.98298904006054, "hamming_distance": 1, "time": 2.9489736557006836}, {"situation": "expected_negative", "greater_p_value": 0.9999996609360445, "lower_p_value": 3.3919934002820615e-07, "main_fitness": -401.6840859158478, "background_fitness": -400.94728256487775, "hamming_distance": 7, "time": 2.9512529373168945}, {"situation": "expected_positive", "greater_p_value": 5.709907481215474e-282, "lower_p_value": 1.0, "main_fitness": -394.40636696900987, "background_fitness": -395.5526778785588, "hamming_distance": 6, "time": 3.0149154663085938}, {"situation": "expected_positive", "greater_p_value": 1.3953640619018138e-103, "lower_p_value": 1.0, "main_fitness": -396.3172520156211, "background_fitness": -396.59725201562105, "hamming_distance": 1, "time": 3.0092484951019287}, {"situation": "expected_negative", "greater_p_value": 1.8789794928163571e-44, "lower_p_value": 1.0, "main_fitness": -395.86711778785593, "background_fitness": -395.1164433106576, "hamming_distance": 6, "time": 3.112556219100952}, {"situation": "expected_positive", "greater_p_value": 0.7777703225597561, "lower_p_value": 0.22225274039435788, "main_fitness": -398.59894822373394, "background_fitness": -398.79346069538923, "hamming_distance": 7, "time": 2.9002089500427246}, {"situation": "expected_negative", "greater_p_value": 1.0, "lower_p_value": 9.708294378454931e-178, "main_fitness": -400.5305879314689, "background_fitness": -394.1107126480222, "hamming_distance": 7, "time": 3.0104317665100098}, {"situation": "expected_positive", "greater_p_value": 0.9992910155656446, "lower_p_value": 0.000709174488536873, "main_fitness": -395.8120547052154, "background_fitness": -396.81700440917115, "hamming_distance": 7, "time": 2.904944896697998}, {"situation": "expected_positive", "greater_p_value": 2.1070393509916034e-125, "lower_p_value": 1.0, "main_fitness": -395.2444438145628, "background_fitness": -395.43394381456284, "hamming_distance": 2, "time": 2.936973810195923}, {"situation": "expected_negative", "greater_p_value": 2.9602206485725334e-19, "lower_p_value": 1.0, "main_fitness": -396.8064309649785, "background_fitness": -396.1151916099774, "hamming_distance": 6, "time": 2.9696195125579834}, {"situation": "expected_positive", "greater_p_value": 5.933760202159448e-16, "lower_p_value": 0.9999999999999994, "main_fitness": -394.43343600403125, "background_fitness": -400.6853246409675, "hamming_distance": 7, "time": 2.873300790786743}, {"situation": "expected_negative", "greater_p_value": 6.37973442069502e-177, "lower_p_value": 1.0, "main_fitness": -394.4555360607206, "background_fitness": -392.83222767069793, "hamming_distance": 6, "time": 2.885300636291504}, {"situation": "expected_negative", "greater_p_value": 1.0, "lower_p_value": 1.1110260909624555e-259, "main_fitness": -398.82756324011086, "background_fitness": -393.46518849206353, "hamming_distance": 7, "time": 2.9330384731292725}, {"situation": "expected_positive", "greater_p_value": 0.9999999999999996, "lower_p_value": 4.749902678139961e-16, "main_fitness": -396.5151137566138, "background_fitness": -396.9532496850592, "hamming_distance": 6, "time": 3.102876901626587}, {"situation": "expected_negative", "greater_p_value": 1.0, "lower_p_value": 1.3216033622750557e-35, "main_fitness": -397.14974137062234, "background_fitness": -396.6897425044092, "hamming_distance": 6, "time": 2.9926044940948486}, {"situation": "expected_positive", "greater_p_value": 4.50673768300948e-270, "lower_p_value": 1.0, "main_fitness": -393.1529953388763, "background_fitness": -393.36279125724366, "hamming_distance": 2, "time": 3.0648841857910156}, {"situation": "expected_negative", "greater_p_value": 3.862322213919711e-21, "lower_p_value": 1.0, "main_fitness": -397.02906449987404, "background_fitness": -395.8053445452255, "hamming_distance": 8, "time": 2.9486589431762695}, {"situation": "expected_negative", "greater_p_value": 1.0, "lower_p_value": 1.5821439162023313e-107, "main_fitness": -398.4923771730914, "background_fitness": -397.9824953388763, "hamming_distance": 4, "time": 3.0450820922851562}, {"situation": "expected_positive", "greater_p_value": 7.790830364380906e-252, "lower_p_value": 1.0, "main_fitness": -393.71353980851603, "background_fitness": -397.0188180901991, "hamming_distance": 6, "time": 2.8825879096984863}, {"situation": "expected_negative", "greater_p_value": 1.0, "lower_p_value": 2.3932216100923732e-204, "main_fitness": -398.3311307634165, "background_fitness": -393.9806820672714, "hamming_distance": 6, "time": 3.010592222213745}, {"situation": "expected_negative", "greater_p_value": 7.602442545926003e-63, "lower_p_value": 1.0, "main_fitness": -394.70032829428067, "background_fitness": -393.6147030738221, "hamming_distance": 6, "time": 2.8484058380126953}, {"situation": "expected_positive", "greater_p_value": 5.445126176143617e-77, "lower_p_value": 1.0, "main_fitness": -397.31208755354, "background_fitness": -398.3852224741749, "hamming_distance": 6, "time": 2.8451123237609863}, {"situation": "expected_negative", "greater_p_value": 0.9999999999997197, "lower_p_value": 2.804708185912249e-13, "main_fitness": -397.3899828672209, "background_fitness": -397.2720486268582, "hamming_distance": 7, "time": 2.87323260307312}, {"situation": "expected_positive", "greater_p_value": 9.495361143918366e-121, "lower_p_value": 1.0, "main_fitness": -395.2442111678005, "background_fitness": -398.7435240614765, "hamming_distance": 8, "time": 2.8495099544525146}, {"situation": "expected_negative", "greater_p_value": 1.0, "lower_p_value": 1.422702381855619e-113, "main_fitness": -397.2880634920635, "background_fitness": -394.38175799949613, "hamming_distance": 5, "time": 2.8726277351379395}, {"situation": "expected_negative", "greater_p_value": 1.0, "lower_p_value": 3.0912491081840967e-280, "main_fitness": -401.01121982867227, "background_fitness": -399.8575670194004, "hamming_distance": 7, "time": 2.835308074951172}, {"situation": "expected_negative", "greater_p_value": 1.0, "lower_p_value": 3.7933600728423826e-255, "main_fitness": -400.353602670698, "background_fitness": -396.59120915217943, "hamming_distance": 5, "time": 2.9251911640167236}, {"situation": "expected_negative", "greater_p_value": 0.3736538317689757, "lower_p_value": 0.6263754995540987, "main_fitness": -397.01268165784836, "background_fitness": -396.03314361300073, "hamming_distance": 7, "time": 2.840287923812866}, {"situation": "expected_positive", "greater_p_value": 1.5578031748308328e-46, "lower_p_value": 1.0, "main_fitness": -396.5835637440161, "background_fitness": -396.78364273116654, "hamming_distance": 6, "time": 2.8434863090515137}, {"situation": "expected_negative", "greater_p_value": 1.0, "lower_p_value": 4.902996776124773e-273, "main_fitness": -400.40448211136305, "background_fitness": -398.183758377425, "hamming_distance": 6, "time": 2.906203508377075}, {"situation": "expected_negative", "greater_p_value": 0.015022741205752116, "lower_p_value": 0.9849801950666621, "main_fitness": -396.6493717561099, "background_fitness": -393.99705316200556, "hamming_distance": 7, "time": 2.8622312545776367}, {"situation": "expected_positive", "greater_p_value": 1.0, "lower_p_value": 1.375261579514985e-42, "main_fitness": -395.69808465608463, "background_fitness": -396.99385563114134, "hamming_distance": 7, "time": 2.8635168075561523}, {"situation": "expected_positive", "greater_p_value": 1.0, "lower_p_value": 2.942266563722567e-39, "main_fitness": -395.2442111678005, "background_fitness": -398.7435240614765, "hamming_distance": 8, "time": 2.8491666316986084}, {"situation": "expected_positive", "greater_p_value": 5.0003853504646705e-101, "lower_p_value": 1.0, "main_fitness": -395.59042139077854, "background_fitness": -398.0099205089444, "hamming_distance": 6, "time": 2.8468918800354004}, {"situation": "expected_positive", "greater_p_value": 9.090332480876248e-92, "lower_p_value": 1.0, "main_fitness": -394.70398513479466, "background_fitness": -394.9895406903502, "hamming_distance": 1, "time": 2.855311632156372}, {"situation": "expected_negative", "greater_p_value": 1.0, "lower_p_value": 5.092116845537906e-143, "main_fitness": -398.89798475686575, "background_fitness": -395.4792755102041, "hamming_distance": 7, "time": 2.829252004623413}, {"situation": "expected_negative", "greater_p_value": 1.0, "lower_p_value": 2.0096961052000494e-216, "main_fitness": -401.47952254976065, "background_fitness": -401.01982237339377, "hamming_distance": 7, "time": 2.916198492050171}, {"situation": "expected_positive", "greater_p_value": 9.592851210845947e-16, "lower_p_value": 0.999999999999999, "main_fitness": -396.4603038548753, "background_fitness": -396.81588410178887, "hamming_distance": 6, "time": 2.830906867980957}, {"situation": "expected_positive", "greater_p_value": 1.7867444180413828e-108, "lower_p_value": 1.0, "main_fitness": -396.0957766439909, "background_fitness": -397.00298526077097, "hamming_distance": 1, "time": 2.884340763092041}, {"situation": "expected_negative", "greater_p_value": 1.0, "lower_p_value": 1.360661911862185e-284, "main_fitness": -400.24375207860925, "background_fitness": -395.4001903502142, "hamming_distance": 1, "time": 2.90920352935791}, {"situation": "expected_positive", "greater_p_value": 4.109092953357005e-31, "lower_p_value": 1.0, "main_fitness": -396.8219412950365, "background_fitness": -398.6252241118669, "hamming_distance": 7, "time": 2.79683780670166}, {"situation": "expected_negative", "greater_p_value": 1.0, "lower_p_value": 1.6413230660555734e-58, "main_fitness": -399.24189833711256, "background_fitness": -398.69262055933484, "hamming_distance": 8, "time": 2.8879778385162354}, {"situation": "expected_positive", "greater_p_value": 1.4158221035555168e-57, "lower_p_value": 1.0, "main_fitness": -393.4782175610986, "background_fitness": -393.79115347064754, "hamming_distance": 6, "time": 2.816357135772705}, {"situation": "expected_positive", "greater_p_value": 2.190865821953683e-84, "lower_p_value": 1.0, "main_fitness": -395.81926858150666, "background_fitness": -396.5475797430083, "hamming_distance": 7, "time": 2.970615863800049}, {"situation": "expected_positive", "greater_p_value": 1.398797965374292e-42, "lower_p_value": 1.0, "main_fitness": -397.4769805996473, "background_fitness": -402.294341521794, "hamming_distance": 8, "time": 2.836247682571411}, {"situation": "expected_positive", "greater_p_value": 5.958014999776952e-29, "lower_p_value": 1.0, "main_fitness": -394.68769085411947, "background_fitness": -394.9119130763417, "hamming_distance": 2, "time": 3.0304489135742188}, {"situation": "expected_positive", "greater_p_value": 1.958011468044881e-157, "lower_p_value": 1.0, "main_fitness": -395.73628458049893, "background_fitness": -396.19832539682545, "hamming_distance": 1, "time": 3.034180164337158}, {"situation": "expected_positive", "greater_p_value": 0.4170232082846509, "lower_p_value": 0.5830070149979601, "main_fitness": -395.9327382212144, "background_fitness": -396.93473116654064, "hamming_distance": 6, "time": 2.8433287143707275}, {"situation": "expected_positive", "greater_p_value": 6.286265928868468e-23, "lower_p_value": 1.0, "main_fitness": -397.31208755354, "background_fitness": -398.3852224741749, "hamming_distance": 6, "time": 2.8626556396484375}, {"situation": "expected_positive", "greater_p_value": 1.498874322704472e-213, "lower_p_value": 1.0, "main_fitness": -394.7252606449987, "background_fitness": -394.8442606449987, "hamming_distance": 1, "time": 2.95735764503479}, {"situation": "expected_negative", "greater_p_value": 1.7129277451346408e-49, "lower_p_value": 1.0, "main_fitness": -396.6493717561099, "background_fitness": -393.99705316200556, "hamming_distance": 7, "time": 2.923081398010254}, {"situation": "expected_positive", "greater_p_value": 1.0, "lower_p_value": 3.561113616333045e-33, "main_fitness": -399.1360706727135, "background_fitness": -400.69484328546235, "hamming_distance": 7, "time": 2.8745083808898926}, {"situation": "expected_positive", "greater_p_value": 1.1401115205092431e-26, "lower_p_value": 1.0, "main_fitness": -395.9735818846057, "background_fitness": -397.52146623834716, "hamming_distance": 6, "time": 2.841886520385742}, {"situation": "expected_negative", "greater_p_value": 0.9995118233066731, "lower_p_value": 0.0004883113208079573, "main_fitness": -396.70789884101794, "background_fitness": -396.11207117661877, "hamming_distance": 2, "time": 2.920243978500366}]