[
    {
        "problem_name": "SAT_L",
        "sample_size": 10000,
        "pRef_method": "Tabu",
        "results_by_tree": [
            {
                "kind": "ps",
                "depth": 3,
                "ps_budget": 5000,
                "ps_population": 100,
                "avoid_ancestors": false,
                "metrics": "variance estimated_atomicity",
                "order_tree": {
                    "own": 5,
                    "matching": {
                        "own": 6,
                        "matching": {
                            "own": 4,
                            "matching": {},
                            "unmatching": {}
                        },
                        "unmatching": {
                            "own": 2,
                            "matching": {},
                            "unmatching": {}
                        }
                    },
                    "unmatching": {
                        "own": 3,
                        "matching": {
                            "own": 4,
                            "matching": {},
                            "unmatching": {}
                        },
                        "unmatching": {
                            "own": 3,
                            "matching": {},
                            "unmatching": {}
                        }
                    }
                },
                "results": {
                    "mse": 16.97494202361981,
                    "mae": 3.244994285986013,
                    "r_sq": 0.14370720388500413,
                    "evs": 0.14370760463478172
                }
            }
        ]
    }
]