[
    {
        "problem_name": "SAT_M",
        "sample_size": 10000,
        "pRef_method": "uniform",
        "results_by_tree": [
            {
                "kind": "ps",
                "depth": 3,
                "ps_budget": 5000,
                "ps_population": 100,
                "avoid_ancestors": false,
                "metrics": "simplicity estimated_atomicity",
                "order_tree": {
                    "own": 1,
                    "matching": {
                        "own": 1,
                        "matching": {
                            "own": 1,
                            "matching": {},
                            "unmatching": {}
                        },
                        "unmatching": {
                            "own": 1,
                            "matching": {},
                            "unmatching": {}
                        }
                    },
                    "unmatching": {
                        "own": 1,
                        "matching": {
                            "own": 1,
                            "matching": {},
                            "unmatching": {}
                        },
                        "unmatching": {
                            "own": 1,
                            "matching": {},
                            "unmatching": {}
                        }
                    }
                },
                "results": {
                    "mse": 25.132160332470782,
                    "mae": 3.970067000728277,
                    "r_sq": 0.033661279369559094,
                    "evs": 0.03415883748715742
                }
            }
        ]
    }
]