[
    {
        "problem_name": "BT",
        "sample_size": 10000,
        "pRef_method": "BBO",
        "results_by_tree": [
            {
                "kind": "ps",
                "depth": 4,
                "ps_budget": 5000,
                "ps_population": 100,
                "avoid_ancestors": false,
                "metrics": "simplicity variance",
                "order_tree": {
                    "own": 4,
                    "matching": {
                        "own": 1,
                        "matching": {
                            "own": 1,
                            "matching": {
                                "own": 2,
                                "matching": {},
                                "unmatching": {}
                            },
                            "unmatching": {
                                "own": 2,
                                "matching": {},
                                "unmatching": {}
                            }
                        },
                        "unmatching": {
                            "own": 1,
                            "matching": {
                                "own": 2,
                                "matching": {},
                                "unmatching": {}
                            },
                            "unmatching": {
                                "own": 2,
                                "matching": {},
                                "unmatching": {}
                            }
                        }
                    },
                    "unmatching": {
                        "own": 2,
                        "matching": {
                            "own": 3,
                            "matching": {
                                "own": 2,
                                "matching": {},
                                "unmatching": {}
                            },
                            "unmatching": {
                                "own": 3,
                                "matching": {},
                                "unmatching": {}
                            }
                        },
                        "unmatching": {
                            "own": 1,
                            "matching": {
                                "own": 2,
                                "matching": {},
                                "unmatching": {}
                            },
                            "unmatching": {
                                "own": 1,
                                "matching": {},
                                "unmatching": {}
                            }
                        }
                    }
                },
                "results": {
                    "mse": 25.511319376054203,
                    "mae": 2.8224234858440678,
                    "r_sq": 0.9268559264704616,
                    "evs": 0.9283245555022918
                }
            }
        ]
    }
]