[
    {
        "problem_name": "SAT_L",
        "sample_size": 10000,
        "pRef_method": "SA",
        "results_by_tree": [
            {
                "kind": "ps",
                "depth": 4,
                "ps_budget": 5000,
                "ps_population": 100,
                "avoid_ancestors": false,
                "metrics": "simplicity variance estimated_atomicity",
                "order_tree": {
                    "own": 2,
                    "matching": {
                        "own": 2,
                        "matching": {
                            "own": 2,
                            "matching": {
                                "own": 4,
                                "matching": {},
                                "unmatching": {}
                            },
                            "unmatching": {
                                "own": 2,
                                "matching": {},
                                "unmatching": {}
                            }
                        },
                        "unmatching": {
                            "own": 6,
                            "matching": {
                                "own": 2,
                                "matching": {},
                                "unmatching": {}
                            },
                            "unmatching": {
                                "own": 1,
                                "matching": {},
                                "unmatching": {}
                            }
                        }
                    },
                    "unmatching": {
                        "own": 4,
                        "matching": {
                            "own": 5,
                            "matching": {
                                "own": 2,
                                "matching": {},
                                "unmatching": {}
                            },
                            "unmatching": {
                                "own": 37,
                                "matching": {},
                                "unmatching": {}
                            }
                        },
                        "unmatching": {
                            "own": 3,
                            "matching": {
                                "own": 2,
                                "matching": {},
                                "unmatching": {}
                            },
                            "unmatching": {
                                "own": 2,
                                "matching": {},
                                "unmatching": {}
                            }
                        }
                    }
                },
                "results": {
                    "mse": 51.87169962522437,
                    "mae": 5.35255877146225,
                    "r_sq": 0.5599795239649707,
                    "evs": 0.5605060673870782
                }
            }
        ]
    }
]