[
    {
        "problem_name": "SAT_S",
        "sample_size": 10000,
        "pRef_method": "BBO",
        "results_by_tree": [
            {
                "kind": "ps",
                "depth": 3,
                "ps_budget": 5000,
                "ps_population": 100,
                "avoid_ancestors": false,
                "metrics": "simplicity variance",
                "order_tree": {
                    "own": 2,
                    "matching": {
                        "own": 2,
                        "matching": {
                            "own": 1,
                            "matching": {},
                            "unmatching": {}
                        },
                        "unmatching": {
                            "own": 1,
                            "matching": {},
                            "unmatching": {}
                        }
                    },
                    "unmatching": {
                        "own": 1,
                        "matching": {
                            "own": 2,
                            "matching": {},
                            "unmatching": {}
                        },
                        "unmatching": {
                            "own": 1,
                            "matching": {},
                            "unmatching": {}
                        }
                    }
                },
                "results": {
                    "mse": 3.595938815281687,
                    "mae": 1.5641436994378177,
                    "r_sq": 0.6655478903801086,
                    "evs": 0.6842949046982088
                }
            }
        ]
    }
]